pgn_to_sqlite/__init__.py
pgn_to_sqlite/cli.py
pgn_to_sqlite-2.2.1.dist-info/METADATA
pgn_to_sqlite-2.2.1.dist-info/WHEEL
pgn_to_sqlite-2.2.1.dist-info/entry_points.txt
pgn_to_sqlite-2.2.1.dist-info/licenses/LICENSE
pgn_to_sqlite-2.2.1.dist-info/RECORD
