Metadata-Version: 2.4
Name: pgn_to_sqlite
Version: 2.2.1
Summary: Pull your Chess games from chess.com and lichess.org into a sqlite3 database.
Project-URL: Home, https://github.com/EndlessTrax/pgn-to-sqlite
Project-URL: Documentation, https://github.com/EndlessTrax/pgn-to-sqlite/blob/master/README.md
Project-URL: Issues, https://github.com/EndlessTrax/pgn-to-sqlite/issues
Author-email: Ricky White <ricky@rickywhite.net>
License: The MIT License (MIT)
License-File: LICENSE
Classifier: License :: OSI Approved :: MIT License
Classifier: Programming Language :: Python :: 3.9
Classifier: Programming Language :: Python :: 3.10
Classifier: Programming Language :: Python :: 3.11
Classifier: Programming Language :: Python :: 3.12
Classifier: Programming Language :: Python :: 3.13
Requires-Python: >=3.9
Requires-Dist: berserk==0.13.2
Requires-Dist: click==8.1.8
Requires-Dist: requests==2.32.3
